[
  {
    "종목코드": "005930",
    "주요주주": "삼성생명보험 외 15인",
    "보유주식수": 1241176035,
    "보유지분": 20.79
  },
  {
    "종목코드": "005930",
    "주요주주": "국민연금공단",
    "보유주식수": 458637667,
    "보유지분": 7.68
  },
  {
    "종목코드": "005930",
    "주요주주": "BlackRock Fund Advisors 외 15인",
    "보유주식수": 300391061,
    "보유지분": 5.03
  },
  {
    "종목코드": "000660",
    "주요주주": "에스케이스퀘어 외 9인",
    "보유주식수": 146125674,
    "보유지분": 20.07
  },
  {
    "종목코드": "000660",
    "주요주주": "국민연금공단",
    "보유주식수": 59508387,
    "보유지분": 8.17
  },
  {
    "종목코드": "000660",
    "주요주주": "The Capital Group Companies, Inc. 외 33인",
    "보유주식수": 36787079,
    "보유지분": 5.05
  },
  {
    "종목코드": "051910",
    "주요주주": "LG 외 2인",
    "보유주식수": 23555557,
    "보유지분": 33.37
  },
  {
    "종목코드": "051910",
    "주요주주": "국민연금공단",
    "보유주식수": 4825752,
    "보유지분": 6.84
  },
  {
    "종목코드": "051910",
    "주요주주": "LG화학",
    "보유주식수": 367529,
    "보유지분": 0.52
  },
  {
    "종목코드": "005380",
    "주요주주": "현대모비스 외 8인",
    "보유주식수": 62781378,
    "보유지분": 29.38
  },
  {
    "종목코드": "005380",
    "주요주주": "국민연금공단",
    "보유주식수": 16629665,
    "보유지분": 7.78
  },
  {
    "종목코드": "005380",
    "주요주주": "현대차",
    "보유주식수": 14902914,
    "보유지분": 6.97
  },
  {
    "종목코드": "000270",
    "주요주주": "현대자동차 외 5인",
    "보유주식수": 144408340,
    "보유지분": 35.62
  },
  {
    "종목코드": "000270",
    "주요주주": "국민연금공단",
    "보유주식수": 30242601,
    "보유지분": 7.46
  },
  {
    "종목코드": "000270",
    "주요주주": "기아",
    "보유주식수": 4432331,
    "보유지분": 1.09
  },
  {
    "종목코드": "005490",
    "주요주주": "국민연금공단",
    "보유주식수": 7606062,
    "보유지분": 8.99
  },
  {
    "종목코드": "005490",
    "주요주주": "BlackRock Fund Advisors 외 13인",
    "보유주식수": 4555963,
    "보유지분": 5.39
  },
  {
    "종목코드": "005490",
    "주요주주": "POSCO홀딩스",
    "보유주식수": 11337658,
    "보유지분": 13.41
  },
  {
    "종목코드": "006400",
    "주요주주": "삼성전자 외 5인",
    "보유주식수": 14129902,
    "보유지분": 20.55
  },
  {
    "종목코드": "006400",
    "주요주주": "국민연금공단",
    "보유주식수": 5869276,
    "보유지분": 8.54
  },
  {
    "종목코드": "006400",
    "주요주주": "BlackRock Fund Advisors 외 13인",
    "보유주식수": 3444030,
    "보유지분": 5.01
  },
  {
    "종목코드": "012330",
    "주요주주": "기아 외 8인",
    "보유주식수": 29673324,
    "보유지분": 31.38
  },
  {
    "종목코드": "012330",
    "주요주주": "국민연금공단",
    "보유주식수": 8987891,
    "보유지분": 9.5
  },
  {
    "종목코드": "012330",
    "주요주주": "미래에셋자산운용 외 9인",
    "보유주식수": 4823219,
    "보유지분": 5.1
  },
  {
    "종목코드": "028260",
    "주요주주": "이재용 외 13인",
    "보유주식수": 63098596,
    "보유지분": 33.76
  },
  {
    "종목코드": "028260",
    "주요주주": "케이씨씨",
    "보유주식수": 17009518,
    "보유지분": 9.1
  },
  {
    "종목코드": "028260",
    "주요주주": "국민연금공단",
    "보유주식수": 14179943,
    "보유지분": 7.59
  },
  {
    "종목코드": "035720",
    "주요주주": "김범수 외 72인",
    "보유주식수": 107572321,
    "보유지분": 24.16
  },
  {
    "종목코드": "035720",
    "주요주주": "국민연금공단",
    "보유주식수": 28574670,
    "보유지분": 6.42
  },
  {
    "종목코드": "035720",
    "주요주주": "MAXIMO PTE",
    "보유주식수": 27999245,
    "보유지분": 6.29
  },
  {
    "종목코드": "068270",
    "주요주주": "셀트리온홀딩스 외 74인",
    "보유주식수": 32106216,
    "보유지분": 22.8
  },
  {
    "종목코드": "068270",
    "주요주주": "국민연금공단",
    "보유주식수": 10416662,
    "보유지분": 7.4
  },
  {
    "종목코드": "068270",
    "주요주주": "셀트리온",
    "보유주식수": 2879013,
    "보유지분": 2.04
  },
  {
    "종목코드": 207940,
    "주요주주": "삼성물산 외 4인",
    "보유주식수": 52935334,
    "보유지분": 74.37
  },
  {
    "종목코드": 207940,
    "주요주주": "국민연금공단",
    "보유주식수": 3986605,
    "보유지분": 5.6
  },
  {
    "종목코드": "000880",
    "주요주주": "김승연 외 10인",
    "보유주식수": 32687768,
    "보유지분": 43.61
  },
  {
    "종목코드": "000880",
    "주요주주": "국민연금공단",
    "보유주식수": 5067286,
    "보유지분": 6.76
  },
  {
    "종목코드": "000880",
    "주요주주": "한화",
    "보유주식수": 6568817,
    "보유지분": 8.76
  },
  {
    "종목코드": "009540",
    "주요주주": "현대중공업지주 외 10인",
    "보유주식수": 25941611,
    "보유지분": 36.65
  },
  {
    "종목코드": "009540",
    "주요주주": "국민연금공단",
    "보유주식수": 4060214,
    "보유지분": 5.74
  },
  {
    "종목코드": "009540",
    "주요주주": "한국조선해양",
    "보유주식수": 58486,
    "보유지분": 0.08
  },
  {
    "종목코드": 105560,
    "주요주주": "국민연금공단",
    "보유주식수": 33830623,
    "보유지분": 8.27
  },
  {
    "종목코드": 105560,
    "주요주주": "BlackRock Fund Advisors 외 13인",
    "보유주식수": 25036666,
    "보유지분": 6.12
  },
  {
    "종목코드": 105560,
    "주요주주": "KB금융",
    "보유주식수": 19262733,
    "보유지분": 4.71
  },
  {
    "종목코드": "035420",
    "주요주주": "국민연금공단",
    "보유주식수": 13406282,
    "보유지분": 8.17
  },
  {
    "종목코드": "035420",
    "주요주주": "BlackRock Fund Advisors 외 13인",
    "보유주식수": 8283195,
    "보유지분": 5.05
  },
  {
    "종목코드": "035420",
    "주요주주": "NAVER",
    "보유주식수": 14441741,
    "보유지분": 8.8
  },
  {
    "종목코드": "032830",
    "주요주주": "삼성물산 외 8인",
    "보유주식수": 90600965,
    "보유지분": 45.3
  },
  {
    "종목코드": "032830",
    "주요주주": "신세계 외 1인",
    "보유주식수": 16144000,
    "보유지분": 8.07
  },
  {
    "종목코드": "032830",
    "주요주주": "국민연금공단",
    "보유주식수": 11696085,
    "보유지분": 5.85
  },
  {
    "종목코드": "003550",
    "주요주주": "구광모 외 29인",
    "보유주식수": 65598735,
    "보유지분": 41.7
  },
  {
    "종목코드": "003550",
    "주요주주": "국민연금공단",
    "보유주식수": 12634332,
    "보유지분": 8.03
  },
  {
    "종목코드": "003550",
    "주요주주": "미래에셋자산운용 외 9인",
    "보유주식수": 8576099,
    "보유지분": 5.45
  },
  {
    "종목코드": "017670",
    "주요주주": "SK 외 12인",
    "보유주식수": 65712503,
    "보유지분": 30.03
  },
  {
    "종목코드": "017670",
    "주요주주": "국민연금공단",
    "보유주식수": 16485854,
    "보유지분": 7.53
  },
  {
    "종목코드": "017670",
    "주요주주": "SK텔레콤",
    "보유주식수": 801091,
    "보유지분": 0.37
  },
  {
    "종목코드": "036570",
    "주요주주": "김택진 외 6인",
    "보유주식수": 2631366,
    "보유지분": 11.99
  },
  {
    "종목코드": "036570",
    "주요주주": "퍼블릭 인베스트먼트 펀드 외 1인",
    "보유주식수": 2032411,
    "보유지분": 9.26
  },
  {
    "종목코드": "036570",
    "주요주주": "넷마블",
    "보유주식수": 1950000,
    "보유지분": 8.88
  }
]